.gitignore
README.md
setup.py
Test_Accelerator.egg-info/PKG-INFO
Test_Accelerator.egg-info/SOURCES.txt
Test_Accelerator.egg-info/dependency_links.txt
Test_Accelerator.egg-info/entry_points.txt
Test_Accelerator.egg-info/top_level.txt
src/__init__.py
src/converter.py
src/makefile_templates.py
src/parse_tools.py
src/parser.py
src/settings.py
src/tests/__init__.py
src/tests/test_parse_tools.py
src/tests/test_data/__init__.py
src/tests/test_data/calcuadora/calcu.sln
src/tests/test_data/calcuadora/calcu.suo
src/tests/test_data/calcuadora/calcu.v12.suo
src/tests/test_data/calcuadora/calcuadora/Calculator.cs
src/tests/test_data/calcuadora/calcuadora/SimpleCalculator.csproj
src/tests/test_data/calcuadora/calcuadora/Properties/AssemblyInfo.cs
src/tests/test_data/calcuadora/calcuadora/bin/Debug/calcuadora.dll
src/tests/test_data/calcuadora/calcuadora/bin/Debug/calcuadora.pdb
src/tests/test_data/calcuadora/calcuadora/obj/Debug/DesignTimeResolveAssemblyReferencesInput.cache
src/tests/test_data/calcuadora/calcuadora/obj/Debug/SimpleCalculator.csproj.FileListAbsolute.txt
src/tests/test_data/calcuadora/calcuadora/obj/Debug/SimpleCalculator.csprojResolveAssemblyReference.cache
src/tests/test_data/calcuadora/calcuadora/obj/Debug/TemporaryGeneratedFile_036C0B5B-1481-4323-8D20-8F5ADCB23D92.cs
src/tests/test_data/calcuadora/calcuadora/obj/Debug/TemporaryGeneratedFile_5937a670-0e60-4077-877b-f7221da3dda1.cs
src/tests/test_data/calcuadora/calcuadora/obj/Debug/TemporaryGeneratedFile_E7A71F73-0F8D-4B9B-B56E-8E70B10BC5D3.cs
src/tests/test_data/calcuadora/calcuadora/obj/Debug/calcuadora.dll
src/tests/test_data/calcuadora/calcuadora/obj/Debug/calcuadora.pdb
src/tests/test_data/calcuadora/calcuadoratests/CalculatorTests.cs
src/tests/test_data/calcuadora/calcuadoratests/CalculatorTests2.cs
src/tests/test_data/calcuadora/calcuadoratests/SimpleCalculatorTests.csproj
src/tests/test_data/calcuadora/calcuadoratests/MoreTests/CalculatorTests3.cs
src/tests/test_data/calcuadora/calcuadoratests/MoreTests/Class1.cs
src/tests/test_data/calcuadora/calcuadoratests/Properties/AssemblyInfo.cs
src/tests/test_data/calcuadora/calcuadoratests/bin/Debug/calcuadora.dll
