Metadata-Version: 1.0
Name: Test-Accelerator
Version: 0.1.1
Summary: Extracts unit test names from source files to GNU makefiles                so you can speed use emake to run your tests
Home-page: https://github.com/TannerBaldus/test_accelerator
Author: Tanner Baldus
Author-email: tbaldus@electric-cloud.com
License: UNKNOWN
Platform: UNKNOWN
